paig/.coveragerc
paig/README.md
paig/VERSION
paig/__init__.py
paig/__main__.py
paig/launcher.py
paig/routers.py
paig/run_unit_test.sh
paig/server.py
paig/alembic_db/README.md
paig/alembic_db/__init__.py
paig/alembic_db/alembic.ini
paig/alembic_db/env.py
paig/alembic_db/script.py.mako
paig/alembic_db/versions/1b4de1560f7a_added_application_key_to_ai_application_.py
paig/alembic_db/versions/1fced03debf8_access_audits_table_added.py
paig/alembic_db/versions/5e805b526efa_add_tenant.py
paig/alembic_db/versions/9249428e19b0_added_encryption_key_table.py
paig/alembic_db/versions/99a43bcdbea1_added_encryption_master_key_table.py
paig/alembic_db/versions/a7d20ed3c5b4_added_governance_service_tables.py
paig/alembic_db/versions/d016d5e1fe5a_initial_migrations.py
paig/api/__init__.py
paig/api/audit/__init__.py
paig/api/audit/routers.py
paig/api/audit/RDS_service/__init__.py
paig/api/audit/RDS_service/rds_service.py
paig/api/audit/RDS_service/db_models/__init__.py
paig/api/audit/RDS_service/db_models/access_audit_model.py
paig/api/audit/RDS_service/db_operations/__init__.py
paig/api/audit/RDS_service/db_operations/access_audit_repository.py
paig/api/audit/api_schemas/__init__.py
paig/api/audit/api_schemas/access_audit_schema.py
paig/api/audit/controllers/__init__.py
paig/api/audit/controllers/data_store_controller.py
paig/api/audit/factory/__init__.py
paig/api/audit/factory/service_interface.py
paig/api/audit/opensearch_service/__init__.py
paig/api/audit/opensearch_service/opensearch_client.py
paig/api/audit/opensearch_service/opensearch_service.py
paig/api/audit/opensearch_service/util/opensearch_util.py
paig/api/authz/__init__.py
paig/api/authz/routers.py
paig/api/authz/authorizer/__init__.py
paig/api/authz/authorizer/base_paig_authorizer.py
paig/api/authz/authorizer/paig_authorizer.py
paig/api/authz/authorizer/backend/__init__.py
paig/api/authz/authorizer/backend/rds_based_paig_authorizer.py
paig/api/authz/authorizer/filter/__init__.py
paig_opensource-0.0.2.dist-info/METADATA
paig_opensource-0.0.2.dist-info/WHEEL
paig_opensource-0.0.2.dist-info/entry_points.txt
paig_opensource-0.0.2.dist-info/licenses/LICENSE
paig_opensource-0.0.2.dist-info/RECORD
