Metadata-Version: 2.3
Name: paig_opensource
Version: 0.0.2
Summary: PAIG Opensource
Project-URL: Homepage, https://github.com/pypa/privacera_paigopensource
Project-URL: Bug Tracker, https://github.com/pypa/privacera_paigopensource/issues
Author-email: Privacera  <support@privacera.com>
License:                                  Apache License
License-File: LICENSE
Keywords: Chatbot,Governance,PAIG,PAIG-OPENSOURCE,Privacy,Security
Classifier: License :: Other/Proprietary License
Classifier: Operating System :: OS Independent
Classifier: Programming Language :: Python :: 3
Requires-Python: >=3.10
Requires-Dist: aiosqlite
Requires-Dist: alembic
Requires-Dist: alt-profanity-check
Requires-Dist: apscheduler
Requires-Dist: bcrypt
Requires-Dist: boto3==1.34.20
Requires-Dist: cryptography==41.0.4
Requires-Dist: fastapi
Requires-Dist: fasteners
Requires-Dist: greenlet
Requires-Dist: httpx
Requires-Dist: jproperties
Requires-Dist: numpy
Requires-Dist: opentelemetry-distro==0.45b0
Requires-Dist: opentelemetry-exporter-otlp==1.24.0
Requires-Dist: passlib
Requires-Dist: presidio-analyzer==2.2.353
Requires-Dist: presidio-anonymizer==2.2.353
Requires-Dist: privacera-shield-common==1.4.0
Requires-Dist: pydantic[email]
Requires-Dist: python-jose
Requires-Dist: pytz
Requires-Dist: sqlalchemy
Requires-Dist: starlette-request-id
Requires-Dist: urllib3
Requires-Dist: uvicorn
Provides-Extra: dev
Requires-Dist: pytest; extra == 'dev'
Requires-Dist: pytest-asyncio; extra == 'dev'
Requires-Dist: pytest-cov; extra == 'dev'
Requires-Dist: pytest-mock; extra == 'dev'
Requires-Dist: uvicorn[standard]; extra == 'dev'
Provides-Extra: opensearch
Requires-Dist: boto3>=1.28.57; extra == 'opensearch'
Requires-Dist: opensearch-py; extra == 'opensearch'
